LICENSE.txt
MANIFEST.in
README.md
requirements.txt
setup.py
bin/h5pyp_dump
bin/test_hdf5_parallel
config/pypi/__init__.py
h5pyp.egg-info/PKG-INFO
h5pyp.egg-info/SOURCES.txt
h5pyp.egg-info/dependency_links.txt
h5pyp.egg-info/requires.txt
h5pyp.egg-info/top_level.txt
hdf5-1.10.6/ACKNOWLEDGMENTS
hdf5-1.10.6/CMakeFilters.cmake
hdf5-1.10.6/CMakeInstallation.cmake
hdf5-1.10.6/CMakeLists.txt
hdf5-1.10.6/COPYING
hdf5-1.10.6/COPYING_LBNL_HDF5
hdf5-1.10.6/CTestConfig.cmake
hdf5-1.10.6/MANIFEST
hdf5-1.10.6/Makefile
hdf5-1.10.6/Makefile.am
hdf5-1.10.6/Makefile.dist
hdf5-1.10.6/Makefile.in
hdf5-1.10.6/README.txt
hdf5-1.10.6/UserMacros.cmake
hdf5-1.10.6/aclocal.m4
hdf5-1.10.6/acsite.m4
hdf5-1.10.6/autogen.sh
hdf5-1.10.6/configure
hdf5-1.10.6/configure.ac
hdf5-1.10.6/bin/COPYING
hdf5-1.10.6/bin/Makefile.am
hdf5-1.10.6/bin/Makefile.in
hdf5-1.10.6/bin/buildhdf5
hdf5-1.10.6/bin/chkmanifest
hdf5-1.10.6/bin/cmakehdf5
hdf5-1.10.6/bin/compile
hdf5-1.10.6/bin/config.guess
hdf5-1.10.6/bin/config.sub
hdf5-1.10.6/bin/depcomp
hdf5-1.10.6/bin/dependencies
hdf5-1.10.6/bin/deploy
hdf5-1.10.6/bin/distdep
hdf5-1.10.6/bin/genparser
hdf5-1.10.6/bin/h5cc.in
hdf5-1.10.6/bin/h5redeploy.in
hdf5-1.10.6/bin/h5vers
hdf5-1.10.6/bin/install-sh
hdf5-1.10.6/bin/iostats
hdf5-1.10.6/bin/locate_sw
hdf5-1.10.6/bin/ltmain.sh
hdf5-1.10.6/bin/make_err
hdf5-1.10.6/bin/make_overflow
hdf5-1.10.6/bin/make_vers
hdf5-1.10.6/bin/makehelp
hdf5-1.10.6/bin/missing
hdf5-1.10.6/bin/mkdirs
hdf5-1.10.6/bin/newer
hdf5-1.10.6/bin/output_filter.sh
hdf5-1.10.6/bin/release
hdf5-1.10.6/bin/restore.sh
hdf5-1.10.6/bin/snapshot
hdf5-1.10.6/bin/test-driver
hdf5-1.10.6/bin/trace
hdf5-1.10.6/bin/yodconfigure
hdf5-1.10.6/bin/batch/ctest.qsub.in.cmake
hdf5-1.10.6/bin/batch/ctestP.lsf.in.cmake
hdf5-1.10.6/bin/batch/ctestP.sl.in.cmake
hdf5-1.10.6/bin/batch/ctestS.lsf.in.cmake
hdf5-1.10.6/bin/batch/ctestS.sl.in.cmake
hdf5-1.10.6/bin/batch/knl_H5detect.sl.in.cmake
hdf5-1.10.6/bin/batch/knl_ctestP.sl.in.cmake
hdf5-1.10.6/bin/batch/knl_ctestS.sl.in.cmake
hdf5-1.10.6/bin/batch/ray_ctestP.lsf.in.cmake
hdf5-1.10.6/bin/batch/ray_ctestS.lsf.in.cmake
hdf5-1.10.6/bin/batch/raybsub
