Metadata-Version: 2.1
Name: h5pyp
Version: 1.10.6.0a1
Summary: HDF5 Parallel Library and h5py Python bindings
Home-page: https://www.hdfgroup.org/
Author: The HDF Group
Author-email: help@hdfgroup.org
Maintainer: Roberto Vidmar
Maintainer-email: rvidmar@inogs.it
License: BSD
Download-URL: https://www.hdfgroup.org/downloads/
Keywords: HDF5,MPI
Platform: POSIX
Classifier: Development Status :: 3 - Alpha
Classifier: Intended Audience :: Developers
Classifier: Intended Audience :: Science/Research
Classifier: License :: OSI Approved :: BSD License
Classifier: Operating System :: POSIX
Classifier: Programming Language :: C
Classifier: Programming Language :: C++
Classifier: Programming Language :: Fortran
Classifier: Programming Language :: Python
Classifier: Topic :: Scientific/Engineering
Classifier: Topic :: Software Development :: Libraries
